pegomancy/generate.py
pegomancy/grammar.py
pegomancy/grammar_items.py
pegomancy/grammar_parser.py
pegomancy/parse.py
pegomancy/reader.py
pegomancy/source_info.py
pegomancy-1.2.0.data/scripts/pegomant
pegomancy-1.2.0.dist-info/LICENSE
pegomancy-1.2.0.dist-info/METADATA
pegomancy-1.2.0.dist-info/WHEEL
pegomancy-1.2.0.dist-info/top_level.txt
pegomancy-1.2.0.dist-info/RECORD
