Metadata-Version: 2.1
Name: pegomancy
Version: 1.2.0
Summary: Yet another parsing thingy
Home-page: https://github.com/doom/pegomancy
Author: Clément Doumergue
Author-email: clement.doumergue@epitech.eu
License: UNKNOWN
Platform: UNKNOWN
Classifier: Programming Language :: Python :: 3
Classifier: License :: OSI Approved :: MIT License
Classifier: Operating System :: OS Independent
